README.md
setup.py
eyepiscripts/__init__.py
eyepiscripts/pyeyepi.py
libeyepi/Camera.py
libeyepi/GPCamera.py
libeyepi/GigECamera.py
libeyepi/PiCamera.py
libeyepi/USBCamera.py
libeyepi/__init__.py
py_eyepi.egg-info/PKG-INFO
py_eyepi.egg-info/SOURCES.txt
py_eyepi.egg-info/dependency_links.txt
py_eyepi.egg-info/entry_points.txt
py_eyepi.egg-info/requires.txt
py_eyepi.egg-info/top_level.txt