Metadata-Version: 1.2
Name: py-eyepi
Version: 0.2.8.post3
Summary: a tool to capture images from dslrs and raspberry pi cameras
Home-page: https://borevitzlab.github.io/py-eyepi/
Author: Gareth Dunstone, Borevitz Lab, Australian Plant Phenomics Facility, TimeScience
Author-email: appf@anu.edu.au
License: GPLv3
Keywords: timelapse,imaging
Platform: UNKNOWN
Classifier: Development Status :: 4 - Beta
Classifier: Environment :: Console
Classifier: Intended Audience :: Science/Research
Classifier: Operating System :: Unix
Classifier: Programming Language :: Python :: 3 :: Only
Requires-Python: >=3.2
